pandas_profiling_cli/__init__.py
pandas_profiling_cli/main.py
pandas_profiling_cli-0.1.0.dist-info/entry_points.txt
pandas_profiling_cli-0.1.0.dist-info/WHEEL
pandas_profiling_cli-0.1.0.dist-info/METADATA
pandas_profiling_cli-0.1.0.dist-info/RECORD
