Metadata-Version: 2.1
Name: pandas-profiling-cli
Version: 0.1.0
Summary: 
Author: fuyutarow
Author-email: fuyutarow@gmail.com
Requires-Python: >=3.8,<4.0
Classifier: Programming Language :: Python :: 3
Classifier: Programming Language :: Python :: 3.8
Requires-Dist: japanize-matplotlib (>=1.0.5,<2.0.0)
Requires-Dist: pandas-profiling (>=2.5.0,<3.0.0)
Requires-Dist: xlrd (>=1.2.0,<2.0.0)
